neura_dual_quaternions/DualQuaternion.py
neura_dual_quaternions/Quaternion.py
neura_dual_quaternions/__init__.py
neura_dual_quaternions-0.0.4.dist-info/LICENSE.txt
neura_dual_quaternions-0.0.4.dist-info/METADATA
neura_dual_quaternions-0.0.4.dist-info/WHEEL
neura_dual_quaternions-0.0.4.dist-info/top_level.txt
neura_dual_quaternions-0.0.4.dist-info/RECORD
